[
  {
    "ContainingType": "APIMongoDB.Controllers.AlunosController",
    "Method": "ObterTodos",
    "RelativePath": "api/Alunos",
    "HttpMethod": "GET",
    "IsController": true,
    "Order": 0,
    "Parameters": [],
    "ReturnTypes": [
      {
        "Type": "System.Collections.Generic.List\u00601[[APIMongoDB.Model.Aluno, APIMongoDB, Version=1.0.0.0, Culture=neutral, PublicKeyToken=null]]",
        "MediaTypes": [
          "text/plain",
          "application/json",
          "text/json"
        ],
        "StatusCode": 200
      }
    ]
  },
  {
    "ContainingType": "APIMongoDB.Controllers.AlunosController",
    "Method": "Criar",
    "RelativePath": "api/Alunos",
    "HttpMethod": "POST",
    "IsController": true,
    "Order": 0,
    "Parameters": [
      {
        "Name": "aluno",
        "Type": "APIMongoDB.Model.Aluno",
        "IsRequired": true
      }
    ],
    "ReturnTypes": [
      {
        "Type": "APIMongoDB.Model.Aluno",
        "MediaTypes": [
          "text/plain",
          "application/json",
          "text/json"
        ],
        "StatusCode": 200
      }
    ]
  },
  {
    "ContainingType": "APIMongoDB.Controllers.AlunosController",
    "Method": "ObterPorId",
    "RelativePath": "api/Alunos/{id}",
    "HttpMethod": "GET",
    "IsController": true,
    "Order": 0,
    "Parameters": [
      {
        "Name": "id",
        "Type": "System.String",
        "IsRequired": true
      }
    ],
    "ReturnTypes": [
      {
        "Type": "APIMongoDB.Model.Aluno",
        "MediaTypes": [
          "text/plain",
          "application/json",
          "text/json"
        ],
        "StatusCode": 200
      }
    ],
    "EndpointName": "ObterAluno"
  },
  {
    "ContainingType": "APIMongoDB.Controllers.AlunosController",
    "Method": "Atualizar",
    "RelativePath": "api/Alunos/{id}",
    "HttpMethod": "PUT",
    "IsController": true,
    "Order": 0,
    "Parameters": [
      {
        "Name": "id",
        "Type": "System.String",
        "IsRequired": true
      },
      {
        "Name": "alunoAtualizado",
        "Type": "APIMongoDB.Model.Aluno",
        "IsRequired": true
      }
    ],
    "ReturnTypes": []
  },
  {
    "ContainingType": "APIMongoDB.Controllers.AlunosController",
    "Method": "Remover",
    "RelativePath": "api/Alunos/{id}",
    "HttpMethod": "DELETE",
    "IsController": true,
    "Order": 0,
    "Parameters": [
      {
        "Name": "id",
        "Type": "System.String",
        "IsRequired": true
      }
    ],
    "ReturnTypes": []
  },
  {
    "ContainingType": "APIMongoDB.Controllers.WeatherForecastController",
    "Method": "Get",
    "RelativePath": "WeatherForecast",
    "HttpMethod": "GET",
    "IsController": true,
    "Order": 0,
    "Parameters": [],
    "ReturnTypes": [
      {
        "Type": "System.Collections.Generic.IEnumerable\u00601[[APIMongoDB.WeatherForecast, APIMongoDB, Version=1.0.0.0, Culture=neutral, PublicKeyToken=null]]",
        "MediaTypes": [
          "text/plain",
          "application/json",
          "text/json"
        ],
        "StatusCode": 200
      }
    ],
    "EndpointName": "GetWeatherForecast"
  }
]